{
  "wild-vs-data-reaper-report-1": {
    "Mage": [
      "PHONETAP’s Solia Reno Mage.png",
      "PHONETAP’s Tempo Mage.png",
      "RamonLH’s Freeze Mage.png",
      "Sjow’s N’Zoth’s Reno Mage.png",
      "Specialist’s Secret Mage.png",
      "Thijs’ Freeze Mage.png"
    ],
    "Druid": [
      "Innervate Egg Druid.png",
      "Lektron’s Jade Druid.png",
      "Regular Egg Druid.png",
      "Skywalker’s Hobgoblin Egg Druid.png"
    ],
    "Rogue": [
      "Malygos Miracle Rogue.png",
      "Midrange Miracle Rogue.png",
      "Pirate Quest Rogue.png",
      "Questing Miracle Rogue.png",
      "Traditional Quest Rogue.png"
    ],
    "Hunter": [
      "Classic Midrange Hunter.png",
      "Face Hunter.png",
      "Mid Secret Hunter.png",
      "N’Zoth Midrange Hunter.png",
      "Rhino Midrange Hunter.png"
    ],
    "Priest": [
      "Capilano’s Dragon Priest.png",
      "Control’s Combo Priest.png",
      "Frodan’s Dragon Priest.png",
      "Sipiwi94’s Reno N’Zoth Priest.png"
    ],
    "Shaman": [
      "Ancestor’s Call Malygos Shaman.png",
      "Auctioneer Malygos Shaman.png",
      "Classic Malygos Shaman.png",
      "Coldstory’s Jade Control-Midrange Shaman.png",
      "Demigod’s Aggro Shaman.png",
      "Evolve Midrange Shaman.png",
      "Jade Aggro-Midrange Shaman.png",
      "Murloc Shaman.png",
      "Reincarnate Control Shaman.png",
      "Sipiwi94’s Reincarnate Control Shaman.png",
      "Specialist’s Aggro Shaman.png",
      "Thing from Below Control Shaman.png"
    ],
    "Paladin": [
      "Control Paladin.png",
      "Curator Midrange Paladin.png",
      "Lemon’s Murloc Paladin.png",
      "Roarr’s Steward Midrange Paladin.png",
      "Secret Paladin.png"
    ],
    "Warlock": [
      "Classic Zoo Warlock.png",
      "Discard Zoo Warlock.png",
      "Doc Rowdy’s N’zoth Reno Warlock.png",
      "Melody4Ever’s Dreadsteed Reno Warlock.png",
      "XCrouton’’s Anti-Aggro Reno Warlock.png"
    ],
    "Warrior": [
      "Control’s Pirate Warrior.png",
      "Dog’s Taunt Warrior.png",
      "Scorpion’s N’Zoth Control Warrior.png"
    ]
  },
  "wild-vs-data-reaper-report-2": {
    "Mage": [
      "Generic Freeze Mage.png",
      "MeknugetZz’ N’Zoth Reno Mage.png",
      "PHONETAP’s Tempo Mage.png",
      "Snou’s Freeze Mage.png",
      "Specialist’s Secret Mage.png"
    ],
    "Druid": [
      "Alb987’s Token Druid.png",
      "Regular Egg Druid.png",
      "Regular Jade Druid.png",
      "SHRoyalBaiZe’s Jade Druid.png"
    ],
    "Rogue": [
      "Capilano’s Giants Miracle Rogue.png",
      "Control’s Questing Miracle Rogue.png",
      "Hoff’s Crystal Rogue.png",
      "SHRoyalBaiZe’s Crystal Rogue.png"
    ],
    "Hunter": [
      "Classic Midrange Hunter.png",
      "Face Hunter.png",
      "Fire Fly Midrange Hunter.png",
      "Mid Secret Hunter.png",
      "N’Zoth Midrange Hunter.png",
      "Rhino Midrange Hunter.png"
    ],
    "Priest": [
      "Capilano’s Dragon Priest.png",
      "Control’s Combo Priest.png",
      "Masinc’s Dragon Reno Priest.png",
      "Sipiwi94’s Reno N’Zoth Priest.png"
    ],
    "Shaman": [
      "Coldstory’s Control Jade Shaman.png",
      "Masinc’s N’Zoth Control Shaman.png",
      "MeknugetZz’s Aggro Shaman.png",
      "Murloc Shaman.png",
      "Oracle’s Midrange Jade Shaman.png",
      "Poach’s OTK Reincarnate Control Shaman.png",
      "Sipiwi94’s Reincarnate Control Shaman.png",
      "Token Shaman.png"
    ],
    "Paladin": [
      "Awedragon’s Midrange Anyfin Paladin.png",
      "Bertik’s Steward Midrange Paladin.png",
      "Chai and Haydumb’s Midrange Paladin.png",
      "Chai’s Secret Paladin.png",
      "Snou’s Control Paladin.png"
    ],
    "Warlock": [
      "Ant’s 12-Win Brawl Zoo Warlock.png",
      "Hurryupidiot’s Reno Warlock.png",
      "Masinc’s N’Zoth Reno Warlock.png",
      "Zed’s Classic Zoo Warlock.png",
      "Zed’s Discard Zoo Warlock.png"
    ],
    "Warrior": [
      "Control’s Pirate Warrior.png",
      "Noriggoon’s Taunt Warrior.png",
      "Scorpion’s Juggernaut Control Warrior.png",
      "Scorpion’s N’Zoth Control Warrior.png",
      "Scorpion’s Taunt Warrior.png"
    ]
  },
  "wild-vs-data-reaper-report-3": {
    "Zoo": [
      "Poach’s Reno Zoo.png",
      "Zed’s Classic Zoo.png"
    ],
    "Mage": [
      "DannyDonut’s Secret Mage.png",
      "Freeze Mage.png",
      "GetMeowth’s Reno Mage.png",
      "Grizzlybayer’s Exodia Mage.png",
      "Tempo Mage.png"
    ],
    "Druid": [
      "Awedragon’s Aggro-Token Druid.png",
      "Chai’s Giants Druid.png",
      "SamAnthony’s Astral Druid.png",
      "XCrouton’s Jade Druid.png"
    ],
    "Rogue": [
      "DannyDonuts’ Jade N’Zoth Rogue.png",
      "Graveyardsmash’s Questing Miracle Rogue.png",
      "ShatteR’s Mill Rogue.png"
    ],
    "Hunter": [
      "Capilano’s Giants hunter.png",
      "Midrange Hunter.png"
    ],
    "Priest": [
      "awedragon’s Reno Priest.png",
      "Big Priest.png",
      "Sipiwi94’s Velen Reno Priest.png"
    ],
    "Shaman": [
      "Awedragon’s Zealot Aggro Shaman.png",
      "Casanova’s Murloc Shaman.png",
      "MekNugetZz’s Twililght Aggro Shaman.png",
      "Poach’s Control Shaman.png",
      "Poach’s Doomhammer Aggro Shaman.png",
      "Xixo’s Token Shaman.png"
    ],
    "Paladin": [
      "Chai’s Murloc Paladin.png",
      "Haydumb’s Midrange Paladin.png",
      "Schmiddy’s Control Paladin.png"
    ],
    "Warrior": [
      "DannyDonuts’ Pirate Warrior.png",
      "Scorpion’s Dead Man’s Hand N’Zoth Warrior.png",
      "Xixo’s Pirate Warrior.png"
    ],
    "Handlock": [
      "Clickpwn’s Naga Handlock.png"
    ],
    "Renolock": [
      "GetMeowth’s Renolock.png"
    ],
    "Discolock": [
      "Zed’s Discolock.png"
    ]
  },
  "wild-vs-data-reaper-report-4": {
    "Mage": [
      "Bananaramic’s Exodia Mage.png",
      "Bananaramic’s Reno Mage.png",
      "Harain’s and Control’s Tempo Mage.png",
      "slizzle466’s Tempo Secret Mage.png"
    ],
    "Druid": [
      "Chai’s Giants Ramp Druid.png",
      "Poach’s Jade Druid.png",
      "slizzle466’s Aggro-Token Druid.png"
    ],
    "Rogue": [
      "Awedragon’s Keleseth Tempo Rogue.png",
      "Bananaramic’s Mill Rogue.png",
      "DannyDonuts’ Jade N’Zoth Rogue.png",
      "Graveyardsmash’s Classic Miracle Rogue.png",
      "Haydumb’s Keleseth Tempo Rogue.png",
      "Holt’s Pirate Oil Tempo Rogue.png",
      "Kohai’s Oil Miracle Rogue.png"
    ],
    "Hunter": [
      "Capilano’s Giants Hunter.png",
      "Control’s Deathrattle Hunter.png",
      "Midrange Hunter.png"
    ],
    "Priest": [
      "Capilano’s Reno Priest.png",
      "Ice’s Inner Fire Priest.png",
      "Roboleg’s Big Priest.png",
      "Sipiwi94’s Reno Priest.png"
    ],
    "Shaman": [
      "Masinc’s Doomhammer Aggro Shaman.png",
      "Murloc Shaman.png",
      "Poach’s Control Shaman.png",
      "Poach’s Malygos Shaman.png",
      "SamAnthony’s Aggro Shaman.png",
      "Xixo’s Token Shaman.png"
    ],
    "Paladin": [
      "Awedragon’s Anyfin Paladin.png",
      "Chai’s Secret Paladin.png",
      "Haydumb’s Anti-Priest Midrange Paladin.png",
      "Haydumb’s Midrange Paladin.png",
      "Schmiddy’s Control Paladin.png",
      "Toymachine’s Murloc Paladin.png"
    ],
    "Warlock": [
      "Atralb’s Demon Disco Zoo Warlock.png",
      "AZSwim’s Demon Zoo Warlock.png",
      "Hurryupidiot’s Reno Warlock.png"
    ],
    "Warrior": [
      "Cursed Blade Pirate Warrior.png",
      "DannyDonuts’ Pirate Warrior.png",
      "Keleseth Pirate Warrior.png",
      "Scorpion’s N’Zoth Control Warrior.png"
    ]
  },
  "wild-vs-data-reaper-report-5": {
    "Mage": [
      "Bananaramic’s Exodia Mage.png",
      "Bananaramic’s Reno Mage.png",
      "Daboss212’s Reno Mage.png",
      "Ko10rino082’s Secret Tempo Mage.png",
      "Laughing’s Freeze Mage.png"
    ],
    "Druid": [
      "Coldstory’s Jade Druid.png",
      "Jonahrah’s Classic Ramp Druid.png",
      "KimiHaSpider’s Mill Ramp Druid.png",
      "slizzle466’s Aggro-Token Druid.png"
    ],
    "Rogue": [
      "Awedragon’s Ship’s Cannon Tempo Rogue.png",
      "Capilano’s Miracle Rogue.png",
      "Ciataccis’s Mill Rogue.png",
      "Hazer’s Keleseth Tempo Rogue.png",
      "Kohai’s Oil Tempo Rogue.png",
      "Poach’s Raptor Jade Rogue.png"
    ],
    "Hunter": [
      "Kenji’s Giants Hunter.png",
      "RenoJackson’s N’Zoth Hunter.png",
      "Scorpion’s Face Hunter.png"
    ],
    "Priest": [
      "AZSwim’s Inner-Fire Priest.png",
      "Capilano’s Dragon Priest.png",
      "Capilano’s Reno Priest.png",
      "cndman’s Big Priest.png",
      "Control’s Inner Fire Priest.png",
      "Grizzlybayer’s Dragon Ascendant Priest.png",
      "Sipiwi94’s Velen Reno Priest.png"
    ],
    "Shaman": [
      "Casanova’s Murloc Shaman.png",
      "GetMeowth’s Doomhammer Aggro Shaman.png",
      "GetMeowth’s Token Evolve Shaman.png",
      "Poach’s Control Shaman.png",
      "Poach’s Malygos Shaman.png",
      "SamAnthony’s Hammer of Twilight Aggro Shaman.png"
    ],
    "Paladin": [
      "Bananaramic’s Anyfin Paladin.png",
      "Bananaramic’s Tempo Dude Paladin.png",
      "Chai’s Secret Paladin.png",
      "GetMeowth’s Murloc Paladin.png",
      "GrizzlyBayer’s Justicar Dude Paladin.png",
      "Haydumb’s Control Paladin.png"
    ],
    "Warlock": [
      "Hurryupidiot’s Reno Warlock.png",
      "Seviang’s Zoo Warlock.png",
      "TitanX’s Demon Zoo Warlock.png"
    ],
    "Warrior": [
      "DannyDonuts’ Pirate Warrior.png",
      "RenoJackson’s N’Zoth Control Warrior.png",
      "Scorpion’s N’Zoth Control Warrior.png",
      "Yang Zhitan’s Pirate Warrior.png"
    ]
  },
  "wild-vs-data-reaper-report-6": {
    "Mage": [
      "Bananaramic’s Burn Aluneth Mage.png",
      "Bananaramic’s Exodia Mage.png",
      "Bananaramic’s Reno Mage.png",
      "ko10rino082’s Tempo Aluneth Mage.png"
    ],
    "Druid": [
      "Poach’s Jade Druid.png",
      "sipiwi94’s Aggro Druid.png",
      "Zeddy’s Malygos Druid.png"
    ],
    "Rogue": [
      "Bananramic’s Tempo Rogue.png",
      "Eon’s Kingsbane Miracle Rogue.png",
      "Kingsbane Mill Rogue.png",
      "N’Zoth Mill Rogue.png",
      "Questing Miracle Rogue.png"
    ],
    "Hunter": [
      "Audrey’s Mad Scientist Aggro Hunter.png",
      "Control’s Tundra Rhino Aggro Hunter.png",
      "GetMeowth’s Midrange Deathrattle Hunter.png"
    ],
    "Priest": [
      "awedragon’s Reno Priest.png",
      "Grizzlybayer’s Spiteful Dragon Priest.png",
      "Grizzlybayer’s Velen Reno Priest.png",
      "Haze’s Inner Fire Combo Dragon Priest.png",
      "RoffleCONCERNEDMOM’s Big Priest.png",
      "slizzle466’s Greedy Big Priest.png"
    ],
    "Shaman": [
      "Bananaramic’s Aggro Shaman.png",
      "GetMeowth’s Evolve Control Shaman.png",
      "GetMeowth’s Murloc Shaman.png",
      "GetMeowth’s Windfury Aggro Shaman.png",
      "Poach’s Malygos Shaman.png",
      "SKKrillin’s Evolve Token Shaman.png",
      "SKKrillin’s Totem Token Shaman.png",
      "Tezzmizzet’s N’Zoth Control Shaman.png"
    ],
    "Paladin": [
      "Bananaramic’s Anyfin Paladin.png",
      "Chai’s Secret Paladin.png",
      "Control’s Aggro Paladin.png",
      "GetMeowth’s Spiteful Murloc Paladin.png",
      "Haydumb’s Aggro Paladin.png",
      "Haydumb’s Dude Paladin.png"
    ],
    "Warlock": [
      "gorky’s Giant Warlock.png",
      "Harain’s Zoo Warlock.png",
      "XCrouton’s Reno Warlock.png"
    ],
    "Warrior": [
      "Awedragon’s Control Warrior.png",
      "Pirate Warrior.png"
    ],
    "Cubelock": [
      "Capiliano’s Cubelock.png",
      "GetMeowth’s Greedy Cubelock.png"
    ]
  },
  "wild-vs-data-reaper-report-7": {
    "Mage": [
      "Bananaramic’s Exodia Mage.png",
      "Bananaramic’s Reno Mage.png",
      "Bananaramic’s Secret Mage.png",
      "slizzle466’s Aluneth Mage.png"
    ],
    "Druid": [
      "GetMeowth’s Jade Druid.png",
      "Jonahrah’s Malygos Druid.png",
      "slizzle466’s Aggro Druid.png"
    ],
    "Rogue": [
      "Bananaramic’s Tempo Rogue.png",
      "Hel’s Kingsbane Rogue.png",
      "Jonahrah’s Miracle Rogue.png"
    ],
    "Hunter": [
      "DannyDonuts’ Spell Hunter.png",
      "MrDollSteak’s Giants Hunter.png",
      "MrDollSteak’s Secret Hunter.png",
      "na0_Yattaze’s Deathrattle Hunter.png",
      "TopoPablo11’s Aggro Hunter.png"
    ],
    "Priest": [
      "ConcernedMom’s Big Priest.png",
      "Control’s Combo Priest.png",
      "Haze’s Combo Priest.png",
      "Sipiwi94’s Reno Priest.png",
      "Spiteful Priest.png"
    ],
    "Shaman": [
      "Control’s Aggro Shaman.png",
      "GetMeowth’s Murloc Shaman.png",
      "Jonahrah’s Aggro Shaman.png",
      "RenoJackson’s Cube Control Shaman.png",
      "RenoJackson’s Evolve Shaman.png"
    ],
    "Paladin": [
      "Banaramic’s Dude Paladin.png",
      "Chai’s Dude Paladin.png",
      "Chai’s Secret Paladin.png",
      "Doc Rowdy’s Control Paladin.png",
      "GetMeowth’s Aggro Murloc Paladin.png",
      "Jonahrah’s Secret Anyfin Paladin.png",
      "Неясыть’s Aggro Paladin.png"
    ],
    "Warlock": [
      "Cooky’s Bloodbloom Zoo Warlock.png",
      "IndianNinja’s Reno Warlock.png",
      "Jonahrah’s Giants Warlock.png",
      "Roffle’s Cube Warlock.png",
      "SighTed’s Reno Warlock.png"
    ],
    "Warrior": [
      "Awedragon’s Control Warrior.png",
      "RenoJackson’s Pirate Warrior.png"
    ]
  },
  "wild-vs-data-reaper-report-8": {
    "Mage": [
      "AZSwim’s Aluneth Mage.png",
      "Bananaramic’s Exodia Mage.png",
      "Bananaramic’s Reno Mage.png"
    ],
    "Druid": [
      "Control’s Egg Aggro Druid.png",
      "GetMeowth’s Jade Druid.png",
      "Jonahrah’s Malygos Druid.png",
      "LazyTitan’s Aggro Druid.png",
      "Poach’s Miracle Druid.png"
    ],
    "Rogue": [
      "Control’s Kingsbane Rogue.png",
      "Dane’s Big Rogue.png",
      "Jonahrah’s Miracle Rogue.png"
    ],
    "Hunter": [
      "GetMeowth’s Aggro Hunter.png",
      "GetMeowth’s Secret Hunter.png",
      "Spell Hunter.png"
    ],
    "Priest": [
      "CONCERNEDMOM’s Big Priest.png",
      "Haze’s Combo Priest.png",
      "Haze’s Dragon Combo Priest.png",
      "HIOCKY’s Dragon Reno Priest.png",
      "Spiteful Priest.png",
      "Xaos’ Control Priest.png"
    ],
    "Shaman": [
      "Control’s Aggro Shaman.png",
      "Ecthelionlotf’s Control Shaman.png"
    ],
    "Paladin": [
      "Banaramic’s Dude Paladin.png",
      "Chai’s Secret Paladin.png",
      "GetMeowth’s Aggro Murloc Paladin.png",
      "Wo1o1o’s Aggro Paladin.png"
    ],
    "Warlock": [
      "GetMeowth’s Giants Warlock.png",
      "Kigo’s Demon Zoo Warlock.png",
      "sipiwi94’s Cube Warlock.png",
      "XCrouton’s Reno Warlock.png"
    ],
    "Warrior": [
      "Awedragon’s Control Warrior.png",
      "Jonahrah’s Pirate Warrior.png",
      "RenoJackson’s Pirate Warrior.png"
    ]
  },
  "wild-vs-data-reaper-report-9": {
    "Mage": [
      "Bananaramic’s Exodia Mage.png",
      "Bananaramic’s Reno Mage.png",
      "GetMeowth’s Aluneth Mage.png"
    ],
    "Druid": [
      "Bananaramic’s Malygos Druid.png",
      "Jonahrah’s Aggro Druid.png",
      "Kohai’s Togwaggle Druid.png",
      "Memnarc’s Jade Druid.png"
    ],
    "Rogue": [
      "Goku’s Odd Rogue.png",
      "XuwangShackdaddy’s Kingsbane Rogue.png"
    ],
    "Hunter": [
      "Applecat’s Kathrena Hunter.png",
      "Gunnolf’s Odd Face Hunter.png",
      "Jonahrah’s Giant Hunter.png",
      "RenoJackson’s Kathrena Cube Hunter.png"
    ],
    "Priest": [
      "Big Priest.png",
      "Dragon Combo Priest.png",
      "Eon’s Control Dragon Priest.png",
      "Haze’s Combo Priest.png",
      "Skylight’s Reno Priest.png",
      "Spiteful Dragon Priest.png"
    ],
    "Shaman": [
      "Awedragon’s Totemcarver Even Shaman.png",
      "Control’s Aggro Shaman.png",
      "Jade Shaman.png",
      "OfMonCala’s Al’Akir Even Shaman.png",
      "RenoJackson’s Even Shaman.png",
      "Shudderwock Shaman.png"
    ],
    "Paladin": [
      "Aoierias’ Odd Paladin.png",
      "chai’s Secret Paladin.png",
      "GetMeowth’s Murloc Paladin.png",
      "Sipiwi94’s Aggro Paladin.png",
      "Slizzle466’s Even Paladin.png"
    ],
    "Warlock": [
      "Dean’s Mountain Giant Cube Warlock.png",
      "MrDollSteak’s Giant Warlock.png",
      "Sipiwi94’s Cube Warlock.png",
      "xcrouton’s Reno Warlock.png"
    ],
    "Warrior": [
      "Control’s Patron Warrior.png",
      "Corbet’s Pirate Rush Warrior.png",
      "Pirate Warrior.png",
      "RenoJackson’s Fatigue Warrior.png"
    ]
  },
  "wild-vs-data-reaper-report-10": {
    "Mage": [
      "Bananaramic’s Exodia Mage.png",
      "Bananaramic’s N’Zoth Reno Mage.png",
      "Spiral’s Aluneth Mage.png"
    ],
    "Druid": [
      "Awedragon’s Jade Druid.png",
      "Awedragon’s Malygos Druid.png",
      "Kohai’s Togwaggle Druid.png"
    ],
    "Rogue": [
      "Carly’s Odd Rogue.png",
      "MadCorvus’s Odd Rogue.png",
      "Shackdaddy’s Kingsbane Rogue.png",
      "Slizzle466’s Face Collector Odd Rogue.png"
    ],
    "Hunter": [
      "Applecat’s Kathrena Hunter.png",
      "Dane’s Deathrattle Reno Hunter.png",
      "Jonahrah’s Spell Hunter.png"
    ],
    "Priest": [
      "Big Priest.png",
      "DannyDonuts’ Midrange Dragon Priest.png",
      "Haze’s Combo Priest.png",
      "Kripparrian’s Mind Blast Quest Priest.png",
      "Sipiwi94’s Combo Reno Priest.png",
      "Spiteful Dragon Priest.png"
    ],
    "Shaman": [
      "Alice’s Reno Shudderwock Shaman.png",
      "Control’s Aggro Shaman.png",
      "Eregost’s Shudderwock Jade Shaman.png",
      "Shuku’s Even Shaman.png",
      "Zalae’s Even Shaman.png"
    ],
    "Paladin": [
      "Aggro Paladin.png",
      "Aoierias’ Odd Paladin.png",
      "GetMeowth’s Murloc Paladin.png",
      "Hail’s Secret Paladin.png",
      "Slizzle466’s Odd Paladin.png",
      "Zalae’s Odd Paladin.png"
    ],
    "Warlock": [
      "Corbett’s Even Warlock.png",
      "Dean’s Reno Warlock.png",
      "GetMeowth’s Cube Warlock.png",
      "H1J0’s Reno Warlock.png",
      "Kigo’s Zoo Warlock.png"
    ],
    "Warrior": [
      "Control’s Patron Warrior.png",
      "Dean’s Fatigue Control Warrior.png",
      "Gunnolf’s Odd Quest Warrior.png",
      "Pirate Warrior.png"
    ]
  },
  "wild-vs-data-reaper-report-11": {
    "Mage": [
      "Bananaramic’s Exodia Mage.png",
      "Bananaramic’s Reno Mage.png",
      "Sipiwi’s Aluneth Freeze Mage.png",
      "Spiral’s Aluneth Mage.png"
    ],
    "Druid": [
      "Awedragon’s Malygos Druid.png",
      "Dean’s Togwaggle Druid.png",
      "xxFroBro45’s Jade Druid.png"
    ],
    "Rogue": [
      "Bananaramic’s Odd Rogue.png",
      "Dean’s Odd Rogue.png",
      "Shackdaddy’s Kingsbane Rogue.png"
    ],
    "Hunter": [
      "Applecat’s Kathrena Secret Hunter.png",
      "Dane’s Reno Deathrattle Hunter.png",
      "Duwinddk’s Recruit Hunter.png",
      "OfMonCala’s Feugen and Stalagg Reno Hunter.png",
      "Romulus’ Spell Hunter.png",
      "Yuma9420’s Secret Hunter.png"
    ],
    "Priest": [
      "Big Priest.png",
      "DannyDonuts’ Dragon Priest.png",
      "Kripparrian’s Mind Blast Quest Priest.png",
      "RenoJackson’s Inner Fire Priest.png",
      "ShockiiGodx’s Big Priest.png",
      "XxFroBro45xX’s Reno Priest.png"
    ],
    "Shaman": [
      "Aggro Shaman.png",
      "Carly’s Even Shaman.png",
      "DannyDonut’s Lifedrinker Shudderwock Shaman.png",
      "Dean’s Even Shaman.png",
      "Eregost’s Jade Shudderwock Shaman.png",
      "Tezzmizzet’s Reno Shudderwock Shaman.png"
    ],
    "Paladin": [
      "Bananaramic’s Aggro Paladin.png",
      "GetMeowth’s Murloc Paladin.png",
      "Hail’s Secret Paladin.png",
      "Sinyaev’s Odd Paladin.png",
      "Slizzle466’s Pirate Odd Paladin.png"
    ],
    "Warlock": [
      "Dean’s Reno Warlock.png",
      "GetMeowth’s Cube Warlock.png",
      "H1J0’s Reno Warlock.png",
      "Jak’s Zoo Warlock.png",
      "Jayden’s Zoo Warlock.png",
      "V1sby’s Dollmaster Cube Warlock.png",
      "XxFroBro45xX’s Even Warlock.png"
    ],
    "Warrior": [
      "Control’s Patron Warrior.png",
      "Control’s Pirate Warrior.png",
      "KeithNumber’s Recruit Warrior.png",
      "パチンコおじさん’s Mill Warrior.png"
    ]
  }
}