{"Paladin":[{"name":"Even Paladin &#x2013; TeamRankstar","cards":[{"dbfId":943,"name":"Blessing of Kings","cnName":"王者祝福","cardSet":"2","img":"blessing-of-kings.small.png","quantity":2,"rarity":"Basic","cost":4},{"dbfId":211,"name":"Sea Giant","cnName":"海巨人","cardSet":"3","img":"sea-giant.small.png","quantity":2,"rarity":"Epic","cost":10},{"dbfId":1786,"name":"Nerubian Egg","cnName":"蛛魔之卵","cardSet":"12","img":"nerubian-egg.small.png","quantity":2,"rarity":"Rare","cost":2},{"dbfId":985,"name":"Dire Wolf Alpha","cnName":"恐狼前锋","cardSet":"3","img":"direwolf-alpha.small.png","quantity":2,"rarity":"Common","cost":2},{"dbfId":754,"name":"Spellbreaker","cnName":"破法者","cardSet":"3","img":"spellbreaker.small.png","quantity":2,"rarity":"Common","cost":4},{"dbfId":567,"name":"Windfury Harpy","cnName":"风怒鹰身人","cardSet":"3","img":"EX1_033.small.png","quantity":1,"rarity":"Common","cost":6},{"dbfId":1781,"name":"Haunted Creeper","cnName":"鬼灵爬行者","cardSet":"12","img":"haunted-creeper.small.png","quantity":2,"rarity":"Common","cost":2},{"dbfId":2026,"name":"Shielded Minibot","cnName":"护盾机器人","cardSet":"13","img":"shield-mini-bot.small.png","quantity":2,"rarity":"Common","cost":2},{"dbfId":2655,"name":"Murloc Knight","cnName":"鱼人骑士","cardSet":"15","img":"murloc-knight.small.png","quantity":2,"rarity":"Common","cost":4},{"dbfId":2889,"name":"Keeper of Uldaman","cnName":"奥达曼守护者","cardSet":"20","img":"keeperofuldaman.small.png","quantity":2,"rarity":"Common","cost":4},{"dbfId":41145,"name":"Sunkeeper Tarim","cnName":"守日者塔林姆","cardSet":"27","img":"sunkeeper-tarim.small.png","quantity":1,"rarity":"Legendary","cost":6},{"dbfId":46102,"name":"Corpsetaker","cnName":"夺尸者","cardSet":"1001","img":"corpsetaker-tab.small.png","quantity":2,"rarity":"Epic","cost":4},{"dbfId":42791,"name":"Nerubian Unraveler","cnName":"蛛魔拆解者","cardSet":"1001","img":"nerubian-unraveler-tab.small.png","quantity":2,"rarity":"Epic","cost":6},{"dbfId":47693,"name":"Genn Greymane","cnName":"吉恩·格雷迈恩","cardSet":"4","img":"genn-greymane-tab.small.png","quantity":1,"rarity":"Legendary","cost":6},{"dbfId":47201,"name":"Silver Sword","cnName":"银剑","cardSet":"1125","img":"silver-sword-tab.small.png","quantity":1,"rarity":"Rare","cost":8},{"dbfId":54038,"name":"Sandwasp Queen","cnName":"沙漠蜂后","cardSet":"1158","img":"sandwasp-queen.small.png","quantity":2,"rarity":"Common","cost":2},{"dbfId":54077,"name":"Serpent Egg","cnName":"海蛇蛋","cardSet":"1158","img":"serpent-egg.small.png","quantity":2,"rarity":"Common","cost":2}],"code":"AAEBAZ8FBLcEucEC4fACzfQCDdMB8gWvB9kH9Q36DeoP3xTJFqfOApboApamA72mAwA="},{"name":"Mech Handbuff Paladin &#x2013; TeamRankstar","cards":[{"dbfId":679,"name":"Divine Favor","cnName":"神恩术","cardSet":"4","img":"divine-favor.small.png","quantity":2,"rarity":"Rare","cost":3},{"dbfId":754,"name":"Spellbreaker","cnName":"破法者","cardSet":"3","img":"spellbreaker.small.png","quantity":1,"rarity":"Common","cost":4},{"dbfId":2053,"name":"Annoy-o-Tron","cnName":"吵吵机器人","cardSet":"13","img":"annoy-o-tron.small.png","quantity":2,"rarity":"Common","cost":2},{"dbfId":2052,"name":"Flying Machine","cnName":"飞行器","cardSet":"13","img":"flying-machine.small.png","quantity":2,"rarity":"Common","cost":3},{"dbfId":2948,"name":"Sir Finley Mrrgglton","cnName":"芬利·莫格顿爵士","cardSet":"20","img":"sirfinleymrrgglton.small.png","quantity":1,"rarity":"Legendary","cost":1},{"dbfId":40567,"name":"Grimestreet Outfitter","cnName":"污手街供货商","cardSet":"25","img":"grimestreet-outfitter.small.png","quantity":2,"rarity":"Common","cost":2},{"dbfId":40371,"name":"Smuggler's Run","cnName":"风驰电掣","cardSet":"25","img":"smugglers-run.small.png","quantity":2,"rarity":"Common","cost":1},{"dbfId":48993,"name":"Annoy-o-Module","cnName":"吵吵模组","cardSet":"1127","img":"annoy-o-module-tab.small.png","quantity":2,"rarity":"Rare","cost":4},{"dbfId":48985,"name":"Crystology","cnName":"水晶学","cardSet":"1127","img":"crystology-tab.small.png","quantity":2,"rarity":"Rare","cost":1},{"dbfId":48536,"name":"Replicating Menace","cnName":"量产型恐吓机","cardSet":"1127","img":"replicating-menace-tab.small.png","quantity":2,"rarity":"Rare","cost":4},{"dbfId":49356,"name":"Wargear","cnName":"战争机兵","cardSet":"1127","img":"wargear-tab.small.png","quantity":2,"rarity":"Common","cost":5},{"dbfId":49184,"name":"Zilliax","cnName":"奇利亚斯","cardSet":"1127","img":"zilliax-tab.small.png","quantity":1,"rarity":"Legendary","cost":5},{"dbfId":48989,"name":"Glowstone Technician","cnName":"亮石技师","cardSet":"1127","img":"glowstone-technician-tab.small.png","quantity":2,"rarity":"Epic","cost":5},{"dbfId":48982,"name":"Glow-Tron","cnName":"格洛顿","cardSet":"1127","img":"glow-tron-tab.small.png","quantity":2,"rarity":"Common","cost":1},{"dbfId":47775,"name":"Skaterbot","cnName":"滑板机器人","cardSet":"1127","img":"skaterbot-tab.small.png","quantity":2,"rarity":"Common","cost":1},{"dbfId":56223,"name":"SN1P-SN4P","cnName":"大铡蟹","cardSet":"1127","img":"SN1P-SN4P.small.png","quantity":1,"rarity":"Legendary","cost":3},{"dbfId":53445,"name":"Micro Mummy","cnName":"微型木乃伊","cardSet":"1158","img":"micro-mummy.small.png","quantity":2,"rarity":"Epic","cost":2}],"code":"AAEBAZ8FBPIFhBeggAOftwMNpwWEEIUQs7sC97wCn/UCmPsC1v4C2f4C3f4C4f4CzIEDxaEDAA=="},{"name":"Odd Paladin &#x2013; slizzle466","cards":[{"dbfId":679,"name":"Divine Favor","cnName":"神恩术","cardSet":"4","img":"divine-favor.small.png","quantity":1,"rarity":"Rare","cost":3},{"dbfId":70,"name":"Blessing of Might","cnName":"力量祝福","cardSet":"2","img":"blessing-of-might.small.png","quantity":2,"rarity":"Basic","cost":1},{"dbfId":559,"name":"Leeroy Jenkins","cnName":"火车王里诺艾","cardSet":"3","img":"leeroy-jenkins.small.png","quantity":1,"rarity":"Legendary","cost":5},{"dbfId":1914,"name":"Loatheb","cnName":"洛欧塞布","cardSet":"12","img":"loatheb.small.png","quantity":1,"rarity":"Legendary","cost":5},{"dbfId":2029,"name":"Muster for Battle","cnName":"作战动员","cardSet":"13","img":"muster-for-battle.small.png","quantity":2,"rarity":"Rare","cost":3},{"dbfId":2028,"name":"Quartermaster","cnName":"军需官","cardSet":"13","img":"quartermaster.small.png","quantity":2,"rarity":"Epic","cost":5},{"dbfId":2515,"name":"Warhorse Trainer","cnName":"战马训练师","cardSet":"15","img":"warhorse-trainer.small.png","quantity":2,"rarity":"Common","cost":3},{"dbfId":38911,"name":"Steward of Darkshire","cnName":"夜色镇执法官","cardSet":"21","img":"steward-of-darkshire.small.png","quantity":2,"rarity":"Rare","cost":3},{"dbfId":38745,"name":"Rallying Blade","cnName":"集结之刃","cardSet":"21","img":"rallying-blade.small.png","quantity":1,"rarity":"Rare","cost":3},{"dbfId":41912,"name":"Lost in the Jungle","cnName":"迷失丛林","cardSet":"27","img":"lost-in-the-jungle.small.png","quantity":2,"rarity":"Common","cost":1},{"dbfId":42467,"name":"Righteous Protector","cnName":"正义保护者","cardSet":"1001","img":"righteous-protector-tab.small.png","quantity":2,"rarity":"Common","cost":1},{"dbfId":45782,"name":"Unidentified Maul","cnName":"未鉴定的重槌","cardSet":"1004","img":"unidentified-maul-tab.small.png","quantity":1,"rarity":"Rare","cost":3},{"dbfId":43515,"name":"Corridor Creeper","cnName":"通道爬行者","cardSet":"1004","img":"corridor-creeper-tab.small.png","quantity":2,"rarity":"Epic","cost":7},{"dbfId":48158,"name":"Baku the Mooneater","cnName":"噬月者巴库","cardSet":"4","img":"baku-the-mooneater-tab.small.png","quantity":1,"rarity":"Legendary","cost":9},{"dbfId":52494,"name":"Never Surrender!","cnName":"永不屈服","cardSet":"1130","img":"never-surrender.small.png","quantity":2,"rarity":"Common","cost":1},{"dbfId":54269,"name":"Beaming Sidekick","cnName":"欢快的同伴","cardSet":"1158","img":"beaming-sidekick.small.png","quantity":2,"rarity":"Common","cost":1},{"dbfId":53832,"name":"Brazen Zealot","cnName":"英勇狂热者","cardSet":"1158","img":"brazen-zealot.small.png","quantity":2,"rarity":"Rare","cost":1},{"dbfId":54013,"name":"Jar Dealer","cnName":"陶罐商人","cardSet":"1158","img":"jar-dealer.small.png","quantity":2,"rarity":"Common","cost":1}],"code":"AAEBAZ8FBq8EpwX6DtmuAtblAp74AgxG7A/tD9MT/68CuMcC48sC+9MCjpoDyKQD/aUD/acDAA=="}],"Mage":[{"name":"Exodia OTK Mage &#x2013; TeamRankstar","cards":[{"dbfId":1080,"name":"Archmage Antonidas","cnName":"大法师安东尼达斯","cardSet":"3","img":"archmage-antonidas.small.png","quantity":1,"rarity":"Legendary","cost":7},{"dbfId":192,"name":"Ice Block","cnName":"寒冰屏障","cardSet":"4","img":"ice-block.small.png","quantity":2,"rarity":"Epic","cost":3},{"dbfId":457,"name":"Blizzard","cnName":"暴风雪","cardSet":"3","img":"blizzard.small.png","quantity":2,"rarity":"Rare","cost":6},{"dbfId":621,"name":"Ice Barrier","cnName":"寒冰护体","cardSet":"3","img":"ice-barrier.small.png","quantity":1,"rarity":"Common","cost":3},{"dbfId":614,"name":"Sorcerer's Apprentice","cnName":"巫师学徒","cardSet":"3","img":"sorcerers-apprentice.small.png","quantity":2,"rarity":"Common","cost":2},{"dbfId":587,"name":"Frost Nova","cnName":"冰霜新星","cardSet":"2","img":"frost-nova.small.png","quantity":2,"rarity":"Basic","cost":3},{"dbfId":555,"name":"Arcane Intellect","cnName":"奥术智慧","cardSet":"2","img":"arcane-intellect.small.png","quantity":2,"rarity":"Basic","cost":3},{"dbfId":138,"name":"Doomsayer","cnName":"末日预言者","cardSet":"3","img":"doomsayer.small.png","quantity":2,"rarity":"Epic","cost":2},{"dbfId":1016,"name":"Coldlight Oracle","cnName":"寒光智者","cardSet":"4","img":"coldlight-oracle.small.png","quantity":2,"rarity":"Rare","cost":3},{"dbfId":1783,"name":"Mad Scientist","cnName":"疯狂的科学家","cardSet":"12","img":"mad-scientist.small.png","quantity":2,"rarity":"Common","cost":2},{"dbfId":2262,"name":"Emperor Thaurissan","cnName":"索瑞森大帝","cardSet":"14","img":"emperor-thauaissan.small.png","quantity":1,"rarity":"Legendary","cost":6},{"dbfId":41690,"name":"Molten Reflection","cnName":"熔岩镜像","cardSet":"27","img":"molten-reflection.small.png","quantity":2,"rarity":"Rare","cost":4},{"dbfId":43193,"name":"Simulacrum","cnName":"模拟幻影","cardSet":"1001","img":"simulacrum-tab.small.png","quantity":1,"rarity":"Epic","cost":3},{"dbfId":45590,"name":"Arcane Artificer","cnName":"奥术工匠","cardSet":"1004","img":"arcane-artifice-tabr.small.png","quantity":2,"rarity":"Common","cost":1},{"dbfId":48692,"name":"Research Project","cnName":"研发计划","cardSet":"1127","img":"research-project-tab.small.png","quantity":2,"rarity":"Common","cost":2},{"dbfId":54772,"name":"Ancient Mysteries","cnName":"远古谜团","cardSet":"1158","img":"ancient-mysteries.small.png","quantity":2,"rarity":"Common","cost":2},{"dbfId":53823,"name":"Flame Ward","cnName":"火焰结界","cardSet":"1158","img":"flame-ward.small.png","quantity":2,"rarity":"Common","cost":3}],"code":"AAEBAf0EBO0EuAjWEbnRAg2KAcAByQOrBMsE5gT4B/cN2sUCluQCtPwCv6QD9KsDAA=="},{"name":"Quest Tempo Mage &#x2013; slizzle466","cards":[{"dbfId":192,"name":"Ice Block","cnName":"寒冰屏障","cardSet":"4","img":"ice-block.small.png","quantity":1,"rarity":"Epic","cost":3},{"dbfId":614,"name":"Sorcerer's Apprentice","cnName":"巫师学徒","cardSet":"3","img":"sorcerers-apprentice.small.png","quantity":2,"rarity":"Common","cost":2},{"dbfId":1084,"name":"Mirror Image","cnName":"镜像","cardSet":"2","img":"mirror-image.small.png","quantity":2,"rarity":"Basic","cost":1},{"dbfId":555,"name":"Arcane Intellect","cnName":"奥术智慧","cardSet":"2","img":"arcane-intellect.small.png","quantity":2,"rarity":"Basic","cost":3},{"dbfId":39426,"name":"Arcane Giant","cnName":"奥术巨人","cardSet":"23","img":"arcane-giant.small.png","quantity":2,"rarity":"Epic","cost":12},{"dbfId":41168,"name":"Open the Waygate","cnName":"打开时空之门","cardSet":"27","img":"open-the-waygate.small.png","quantity":1,"rarity":"Legendary","cost":1},{"dbfId":41496,"name":"Primordial Glyph","cnName":"远古雕文","cardSet":"27","img":"primordial-glyph.small.png","quantity":2,"rarity":"Epic","cost":2},{"dbfId":47982,"name":"Stargazer Luna","cnName":"观星者露娜","cardSet":"1127","img":"stargazer-luna-tab.small.png","quantity":1,"rarity":"Legendary","cost":3},{"dbfId":48692,"name":"Research Project","cnName":"研发计划","cardSet":"1127","img":"research-project-tab.small.png","quantity":2,"rarity":"Common","cost":2},{"dbfId":50120,"name":"Elemental Evocation","cnName":"元素唤醒","cardSet":"1129","img":"elemental-evocation.small.png","quantity":2,"rarity":"Common","cost":0},{"dbfId":52438,"name":"Archmage Vargoth","cnName":"大法师瓦格斯","cardSet":"1130","img":"archmage-vargoth.small.png","quantity":1,"rarity":"Legendary","cost":4},{"dbfId":52991,"name":"Magic Trick","cnName":"魔术戏法","cardSet":"1130","img":"magic-trick.small.png","quantity":2,"rarity":"Rare","cost":1},{"dbfId":52706,"name":"Mana Cyclone","cnName":"法力飓风","cardSet":"1130","img":"mana-cyclone.small.png","quantity":2,"rarity":"Epic","cost":2},{"dbfId":52639,"name":"Ray of Frost","cnName":"霜冻射线","cardSet":"1130","img":"ray-of-frost.small.png","quantity":2,"rarity":"Common","cost":1},{"dbfId":54772,"name":"Ancient Mysteries","cnName":"远古谜团","cardSet":"1158","img":"ancient-mysteries.small.png","quantity":2,"rarity":"Common","cost":2},{"dbfId":53823,"name":"Flame Ward","cnName":"火焰结界","cardSet":"1158","img":"flame-ward.small.png","quantity":2,"rarity":"Common","cost":3}],"code":"AAEBAf0EBMAB0MEC7vYC1pkDDasE5gS8COMRgrQCmMQCtPwCyIcDn5sD4psD/50Dv6QD9KsDAA=="}],"Hunter":[{"name":"Beast OTK Hunter &#x2013; TeamRankstar","cards":[{"dbfId":1662,"name":"Eaglehorn Bow","cnName":"鹰角弓","cardSet":"3","img":"eaglehorn-bow.small.png","quantity":2,"rarity":"Rare","cost":3},{"dbfId":699,"name":"Tundra Rhino","cnName":"苔原犀牛","cardSet":"2","img":"tundra-rhino.small.png","quantity":2,"rarity":"Basic","cost":5},{"dbfId":1047,"name":"Tracking","cnName":"追踪术","cardSet":"2","img":"tracking.small.png","quantity":2,"rarity":"Basic","cost":1},{"dbfId":2017,"name":"Gahz'rilla","cnName":"加兹瑞拉","cardSet":"13","img":"gahzrilla.small.png","quantity":1,"rarity":"Legendary","cost":7},{"dbfId":2641,"name":"Bear Trap","cnName":"捕熊陷阱","cardSet":"15","img":"bear-trap.small.png","quantity":2,"rarity":"Common","cost":2},{"dbfId":38377,"name":"On the Hunt","cnName":"搜寻猎物","cardSet":"21","img":"on-the-hunt.small.png","quantity":2,"rarity":"Common","cost":1},{"dbfId":43398,"name":"Deathstalker Rexxar","cnName":"死亡猎手雷克萨","cardSet":"1001","img":"deathstalker-rexxar-tab.small.png","quantity":1,"rarity":"Legendary","cost":6},{"dbfId":42525,"name":"Venomstrike Trap","cnName":"眼镜蛇陷阱","cardSet":"1001","img":"venomstrike-trap-tab.small.png","quantity":2,"rarity":"Rare","cost":2},{"dbfId":43359,"name":"Wandering Monster","cnName":"游荡怪物","cardSet":"1004","img":"wandering-monster-tab.small.png","quantity":2,"rarity":"Rare","cost":2},{"dbfId":48201,"name":"Dire Frenzy","cnName":"凶猛狂暴","cardSet":"1125","img":"dire-frenzy-tab.small.png","quantity":2,"rarity":"Common","cost":4},{"dbfId":50212,"name":"Master's Call","cnName":"主人的召唤","cardSet":"1129","img":"masters-call.small.png","quantity":2,"rarity":"Epic","cost":3},{"dbfId":52076,"name":"Rapid Fire","cnName":"急速射击","cardSet":"1130","img":"rapid-fire.small.png","quantity":2,"rarity":"Common","cost":1},{"dbfId":53922,"name":"Hyena Alpha","cnName":"土狼头领","cardSet":"1158","img":"hyena-alpha.small.png","quantity":2,"rarity":"Rare","cost":4},{"dbfId":53919,"name":"Pressure Plate","cnName":"压感陷阱","cardSet":"1158","img":"pressure-plate.small.png","quantity":2,"rarity":"Common","cost":2},{"dbfId":53609,"name":"Scarlet Webweaver","cnName":"猩红织网蛛","cardSet":"1158","img":"scarlet-webweaver.small.png","quantity":2,"rarity":"Epic","cost":6},{"dbfId":53435,"name":"Wild Bloodstinger","cnName":"刺血狂蝎","cardSet":"1158","img":"wild-bloodstinger.small.png","quantity":2,"rarity":"Epic","cost":6}],"code":"AAEBAR8C4Q+G0wIOuwWXCP4M0RTpqwKdzALf0gLJ+AKkiAPslgO7oQPpogOfpQOipQMA"}],"Druid":[{"name":"OTK Linecracker Druid &#x2013; TeamRankstar","cards":[{"dbfId":254,"name":"Innervate","cnName":"激活","cardSet":"2","img":"innervate.small.png","quantity":1,"rarity":"Basic","cost":0},{"dbfId":1802,"name":"Poison Seeds","cnName":"剧毒之种","cardSet":"12","img":"poison-seed.small.png","quantity":2,"rarity":"Common","cost":4},{"dbfId":86,"name":"Starfall","cnName":"星辰坠落","cardSet":"3","img":"starfall.small.png","quantity":2,"rarity":"Rare","cost":5},{"dbfId":40372,"name":"Jade Idol","cnName":"青玉护符","cardSet":"25","img":"jade-idol.small.png","quantity":1,"rarity":"Rare","cost":1},{"dbfId":42656,"name":"Spreading Plague","cnName":"传播瘟疫","cardSet":"1001","img":"spreading-plague-tab.small.png","quantity":2,"rarity":"Rare","cost":6},{"dbfId":42759,"name":"Ultimate Infestation","cnName":"终极感染","cardSet":"1001","img":"ultimate-infestation-tab.small.png","quantity":1,"rarity":"Epic","cost":10},{"dbfId":43417,"name":"Malfurion the Pestilent","cnName":"污染者玛法里奥","cardSet":"1001","img":"malfurion-the-pestilent-tab.small.png","quantity":1,"rarity":"Legendary","cost":7},{"dbfId":43288,"name":"Lesser Jasper Spellstone","cnName":"小型法术玉石","cardSet":"1004","img":"lesser-jasper-spellstone-tab.small.png","quantity":2,"rarity":"Rare","cost":1},{"dbfId":43294,"name":"Branching Paths","cnName":"分岔路口","cardSet":"1004","img":"branching-paths-tab.small.png","quantity":2,"rarity":"Epic","cost":4},{"dbfId":43483,"name":"Arcane Tyrant","cnName":"奥术统御者","cardSet":"1004","img":"arcane-tyrant-tab.small.png","quantity":2,"rarity":"Epic","cost":5},{"dbfId":43284,"name":"Ironwood Golem","cnName":"铁木魔像","cardSet":"1004","img":"ironwood-golem-tab.small.png","quantity":2,"rarity":"Common","cost":4},{"dbfId":45828,"name":"Oaken Summons","cnName":"橡树的召唤","cardSet":"1004","img":"oaken-summons-tab.small.png","quantity":2,"rarity":"Common","cost":4},{"dbfId":47423,"name":"Ferocious Howl","cnName":"凶猛咆哮","cardSet":"1125","img":"ferocious-howl.small.png","quantity":1,"rarity":"Common","cost":3},{"dbfId":50416,"name":"Linecracker","cnName":"阵线破坏者","cardSet":"1129","img":"linecracker.small.png","quantity":2,"rarity":"Epic","cost":7},{"dbfId":52438,"name":"Archmage Vargoth","cnName":"大法师瓦格斯","cardSet":"1130","img":"archmage-vargoth.small.png","quantity":1,"rarity":"Legendary","cost":4},{"dbfId":53615,"name":"Anubisath Defender","cnName":"阿努比萨斯防御者","cardSet":"1158","img":"anubisath-defender.small.png","quantity":2,"rarity":"Epic","cost":5},{"dbfId":53551,"name":"BEEEES!!!","cnName":"蜂群来袭","cardSet":"1158","img":"beeees.small.png","quantity":2,"rarity":"Common","cost":3},{"dbfId":53979,"name":"Overflow","cnName":"溢流","cardSet":"1158","img":"overflow.small.png","quantity":2,"rarity":"Rare","cost":7}],"code":"AAEBAZICBv4BtLsCh84CmdMCv/IC1pkDDFaKDqDNApTSApjSAp7SAtvTAoTmAvCJA6+iA++iA9ulAwA="},{"name":"Taunt Druid &#x2013; TeamRankstar","cards":[{"dbfId":233,"name":"Naturalize","cnName":"自然平衡","cardSet":"4","img":"naturalize.small.png","quantity":2,"rarity":"Common","cost":1},{"dbfId":254,"name":"Innervate","cnName":"激活","cardSet":"2","img":"innervate.small.png","quantity":2,"rarity":"Basic","cost":0},{"dbfId":1802,"name":"Poison Seeds","cnName":"剧毒之种","cardSet":"12","img":"poison-seed.small.png","quantity":2,"rarity":"Common","cost":4},{"dbfId":1790,"name":"Deathlord","cnName":"死亡领主","cardSet":"12","img":"deathlord.small.png","quantity":2,"rarity":"Rare","cost":3},{"dbfId":86,"name":"Starfall","cnName":"星辰坠落","cardSet":"3","img":"starfall.small.png","quantity":2,"rarity":"Rare","cost":5},{"dbfId":2003,"name":"Malorne","cnName":"玛洛恩","cardSet":"13","img":"malorne.small.png","quantity":1,"rarity":"Legendary","cost":7},{"dbfId":43439,"name":"Hadronox","cnName":"哈多诺克斯","cardSet":"1001","img":"hadranox-tab.small.png","quantity":1,"rarity":"Legendary","cost":9},{"dbfId":42656,"name":"Spreading Plague","cnName":"传播瘟疫","cardSet":"1001","img":"spreading-plague-tab.small.png","quantity":2,"rarity":"Rare","cost":6},{"dbfId":42818,"name":"The Lich King","cnName":"巫妖王","cardSet":"1001","img":"the-lich-king-tab.small.png","quantity":1,"rarity":"Legendary","cost":8},{"dbfId":43294,"name":"Branching Paths","cnName":"分岔路口","cardSet":"1004","img":"branching-paths-tab.small.png","quantity":2,"rarity":"Epic","cost":4},{"dbfId":45828,"name":"Oaken Summons","cnName":"橡树的召唤","cardSet":"1004","img":"oaken-summons-tab.small.png","quantity":2,"rarity":"Common","cost":4},{"dbfId":47557,"name":"Rotten Applebaum","cnName":"腐烂的苹果树","cardSet":"1125","img":"rotten-applebaum-tab.small.png","quantity":2,"rarity":"Common","cost":5},{"dbfId":48524,"name":"Juicy Psychmelon","cnName":"香甜的灵力瓜","cardSet":"1127","img":"juicy-psychmelon-tab.small.png","quantity":1,"rarity":"Epic","cost":4},{"dbfId":49184,"name":"Zilliax","cnName":"奇利亚斯","cardSet":"1127","img":"zilliax-tab.small.png","quantity":1,"rarity":"Legendary","cost":5},{"dbfId":52438,"name":"Archmage Vargoth","cnName":"大法师瓦格斯","cardSet":"1130","img":"archmage-vargoth.small.png","quantity":1,"rarity":"Legendary","cost":4},{"dbfId":53615,"name":"Anubisath Defender","cnName":"阿努比萨斯防御者","cardSet":"1158","img":"anubisath-defender.small.png","quantity":2,"rarity":"Epic","cost":5},{"dbfId":53409,"name":"Khartut Defender","cnName":"卡塔图防御者","cardSet":"1158","img":"khartut-defender.small.png","quantity":1,"rarity":"Rare","cost":6},{"dbfId":53979,"name":"Overflow","cnName":"溢流","cardSet":"1158","img":"overflow.small.png","quantity":2,"rarity":"Rare","cost":7}],"code":"AAEBAZICCNMP4KwCws4Cr9MCjPsCoIAD1pkDoaEDC1bpAf4B/g2KDqDNAp7SAoTmAsXzAu+iA9ulAwA="},{"name":"Togwaggle Druid &#x2013; TeamRankstar","cards":[{"dbfId":254,"name":"Innervate","cnName":"激活","cardSet":"2","img":"innervate.small.png","quantity":2,"rarity":"Basic","cost":0},{"dbfId":1802,"name":"Poison Seeds","cnName":"剧毒之种","cardSet":"12","img":"poison-seed.small.png","quantity":2,"rarity":"Common","cost":4},{"dbfId":86,"name":"Starfall","cnName":"星辰坠落","cardSet":"3","img":"starfall.small.png","quantity":2,"rarity":"Rare","cost":5},{"dbfId":2796,"name":"Aviana","cnName":"艾维娜","cardSet":"15","img":"aviana.small.png","quantity":1,"rarity":"Legendary","cost":10},{"dbfId":40523,"name":"Jade Blossom","cnName":"青玉绽放","cardSet":"25","img":"jade-blossom.small.png","quantity":2,"rarity":"Common","cost":3},{"dbfId":42656,"name":"Spreading Plague","cnName":"传播瘟疫","cardSet":"1001","img":"spreading-plague-tab.small.png","quantity":2,"rarity":"Rare","cost":6},{"dbfId":43417,"name":"Malfurion the Pestilent","cnName":"污染者玛法里奥","cardSet":"1001","img":"malfurion-the-pestilent-tab.small.png","quantity":1,"rarity":"Legendary","cost":7},{"dbfId":43288,"name":"Lesser Jasper Spellstone","cnName":"小型法术玉石","cardSet":"1004","img":"lesser-jasper-spellstone-tab.small.png","quantity":2,"rarity":"Rare","cost":1},{"dbfId":43294,"name":"Branching Paths","cnName":"分岔路口","cardSet":"1004","img":"branching-paths-tab.small.png","quantity":2,"rarity":"Epic","cost":4},{"dbfId":46589,"name":"King Togwaggle","cnName":"托瓦格尔国王","cardSet":"1004","img":"kingtogwaggle-tab.small.png","quantity":1,"rarity":"Legendary","cost":8},{"dbfId":43284,"name":"Ironwood Golem","cnName":"铁木魔像","cardSet":"1004","img":"ironwood-golem-tab.small.png","quantity":2,"rarity":"Common","cost":4},{"dbfId":45828,"name":"Oaken Summons","cnName":"橡树的召唤","cardSet":"1004","img":"oaken-summons-tab.small.png","quantity":2,"rarity":"Common","cost":4},{"dbfId":46874,"name":"Azalina Soulthief","cnName":"窃魂者阿扎莉娜","cardSet":"1125","img":"azaline-soultheif-tab.small.png","quantity":1,"rarity":"Legendary","cost":7},{"dbfId":47423,"name":"Ferocious Howl","cnName":"凶猛咆哮","cardSet":"1125","img":"ferocious-howl.small.png","quantity":2,"rarity":"Common","cost":3},{"dbfId":52438,"name":"Archmage Vargoth","cnName":"大法师瓦格斯","cardSet":"1130","img":"archmage-vargoth.small.png","quantity":1,"rarity":"Legendary","cost":4},{"dbfId":52954,"name":"Jepetto Joybuzz","cnName":"耶比托·乔巴斯","cardSet":"1130","img":"jepetto-joybuzz.small.png","quantity":1,"rarity":"Legendary","cost":8},{"dbfId":53979,"name":"Overflow","cnName":"溢流","cardSet":"1158","img":"overflow.small.png","quantity":2,"rarity":"Rare","cost":7}],"code":"AAEBAZICCNYR7BXguwKZ0wL96wKa7gLWmQPanQMLVv4Big7LvAKgzQKU0gKY0gKe0gKE5gK/8gLbpQMA"},{"name":"Jade Druid &#x2013; TeamRankstar","cards":[{"dbfId":1802,"name":"Poison Seeds","cnName":"剧毒之种","cardSet":"12","img":"poison-seed.small.png","quantity":2,"rarity":"Common","cost":4},{"dbfId":86,"name":"Starfall","cnName":"星辰坠落","cardSet":"3","img":"starfall.small.png","quantity":2,"rarity":"Rare","cost":5},{"dbfId":40596,"name":"Aya Blackpaw","cnName":"艾雅·黑掌","cardSet":"25","img":"aya-blackpaw.small.png","quantity":1,"rarity":"Legendary","cost":6},{"dbfId":40523,"name":"Jade Blossom","cnName":"青玉绽放","cardSet":"25","img":"jade-blossom.small.png","quantity":2,"rarity":"Common","cost":3},{"dbfId":40372,"name":"Jade Idol","cnName":"青玉护符","cardSet":"25","img":"jade-idol.small.png","quantity":2,"rarity":"Rare","cost":1},{"dbfId":42656,"name":"Spreading Plague","cnName":"传播瘟疫","cardSet":"1001","img":"spreading-plague-tab.small.png","quantity":2,"rarity":"Rare","cost":6},{"dbfId":42759,"name":"Ultimate Infestation","cnName":"终极感染","cardSet":"1001","img":"ultimate-infestation-tab.small.png","quantity":2,"rarity":"Epic","cost":10},{"dbfId":43417,"name":"Malfurion the Pestilent","cnName":"污染者玛法里奥","cardSet":"1001","img":"malfurion-the-pestilent-tab.small.png","quantity":1,"rarity":"Legendary","cost":7},{"dbfId":43288,"name":"Lesser Jasper Spellstone","cnName":"小型法术玉石","cardSet":"1004","img":"lesser-jasper-spellstone-tab.small.png","quantity":2,"rarity":"Rare","cost":1},{"dbfId":43294,"name":"Branching Paths","cnName":"分岔路口","cardSet":"1004","img":"branching-paths-tab.small.png","quantity":2,"rarity":"Epic","cost":4},{"dbfId":43483,"name":"Arcane Tyrant","cnName":"奥术统御者","cardSet":"1004","img":"arcane-tyrant-tab.small.png","quantity":1,"rarity":"Epic","cost":5},{"dbfId":43284,"name":"Ironwood Golem","cnName":"铁木魔像","cardSet":"1004","img":"ironwood-golem-tab.small.png","quantity":2,"rarity":"Common","cost":4},{"dbfId":45828,"name":"Oaken Summons","cnName":"橡树的召唤","cardSet":"1004","img":"oaken-summons-tab.small.png","quantity":2,"rarity":"Common","cost":4},{"dbfId":47423,"name":"Ferocious Howl","cnName":"凶猛咆哮","cardSet":"1125","img":"ferocious-howl.small.png","quantity":2,"rarity":"Common","cost":3},{"dbfId":52438,"name":"Archmage Vargoth","cnName":"大法师瓦格斯","cardSet":"1130","img":"archmage-vargoth.small.png","quantity":1,"rarity":"Legendary","cost":4},{"dbfId":53615,"name":"Anubisath Defender","cnName":"阿努比萨斯防御者","cardSet":"1158","img":"anubisath-defender.small.png","quantity":2,"rarity":"Epic","cost":5},{"dbfId":53979,"name":"Overflow","cnName":"溢流","cardSet":"1158","img":"overflow.small.png","quantity":2,"rarity":"Rare","cost":7}],"code":"AAEBAZICBJS9ApnTAtvTAtaZAw1Wig60uwLLvAKgzQKHzgKU0gKY0gKe0gKE5gK/8gLvogPbpQMA"}],"Rogue":[{"name":"Odd Rogue &#x2013; slizzle466","cards":[{"dbfId":559,"name":"Leeroy Jenkins","cnName":"火车王里诺艾","cardSet":"3","img":"leeroy-jenkins.small.png","quantity":1,"rarity":"Legendary","cost":5},{"dbfId":724,"name":"Southsea Deckhand","cnName":"南海船工","cardSet":"3","img":"southsea-deckhand.small.png","quantity":2,"rarity":"Common","cost":1},{"dbfId":1914,"name":"Loatheb","cnName":"洛欧塞布","cardSet":"12","img":"loatheb.small.png","quantity":1,"rarity":"Legendary","cost":5},{"dbfId":2291,"name":"Dark Iron Skulker","cnName":"黑铁潜藏者","cardSet":"14","img":"dark-iron-skulker.small.png","quantity":2,"rarity":"Rare","cost":5},{"dbfId":2715,"name":"Buccaneer","cnName":"锈水海盗","cardSet":"15","img":"buccaneer.small.png","quantity":2,"rarity":"Common","cost":1},{"dbfId":40465,"name":"Patches the Pirate","cnName":"海盗帕奇斯","cardSet":"25","img":"patches-the-pirate.small.png","quantity":1,"rarity":"Legendary","cost":1},{"dbfId":41217,"name":"Vilespine Slayer","cnName":"邪脊吞噬者","cardSet":"27","img":"vilespine-slayer.small.png","quantity":2,"rarity":"Epic","cost":5},{"dbfId":45265,"name":"Fungalmancer","cnName":"菌菇术士","cardSet":"1004","img":"fungalmancer-tab.small.png","quantity":2,"rarity":"Common","cost":5},{"dbfId":48158,"name":"Baku the Mooneater","cnName":"噬月者巴库","cardSet":"4","img":"baku-the-mooneater-tab.small.png","quantity":1,"rarity":"Legendary","cost":9},{"dbfId":47014,"name":"Hench-Clan Thug","cnName":"荆棘帮暴徒","cardSet":"1125","img":"hench-clan-thug-tab.small.png","quantity":2,"rarity":"Common","cost":3},{"dbfId":49184,"name":"Zilliax","cnName":"奇利亚斯","cardSet":"1127","img":"zilliax-tab.small.png","quantity":1,"rarity":"Legendary","cost":5},{"dbfId":52111,"name":"EVIL Miscreant","cnName":"怪盗恶霸","cardSet":"1130","img":"evil-miscreant.small.png","quantity":2,"rarity":"Common","cost":3},{"dbfId":53173,"name":"Magic Carpet","cnName":"魔法飞毯","cardSet":"1130","img":"magic-carpet.small.png","quantity":2,"rarity":"Epic","cost":3},{"dbfId":56223,"name":"SN1P-SN4P","cnName":"大铡蟹","cardSet":"1127","img":"SN1P-SN4P.small.png","quantity":1,"rarity":"Legendary","cost":3},{"dbfId":54015,"name":"Hooked Scimitar","cnName":"钩镰弯刀","cardSet":"1158","img":"hooked-scimitar.small.png","quantity":2,"rarity":"Common","cost":3},{"dbfId":54261,"name":"Pharaoh Cat","cnName":"法老御猫","cardSet":"1158","img":"pharaoh-cat.small.png","quantity":2,"rarity":"Common","cost":1},{"dbfId":54426,"name":"Plague of Madness","cnName":"疯狂之灾祸","cardSet":"1158","img":"plague-of-madness.small.png","quantity":2,"rarity":"Rare","cost":1}],"code":"AAEBAaIHBq8E+g6RvAKe+AKggAOftwMM1AXzEZsVkrYCgcIC0eECpu8Cj5cDtZ8D/6UD9acDmqkDAA=="}],"Shaman":[{"name":"Even Shaman &#x2013; slizzle466","cards":[{"dbfId":211,"name":"Sea Giant","cnName":"海巨人","cardSet":"3","img":"sea-giant.small.png","quantity":2,"rarity":"Epic","cost":10},{"dbfId":2006,"name":"Crackle","cnName":"连环爆裂","cardSet":"13","img":"crackle.small.png","quantity":1,"rarity":"Common","cost":2},{"dbfId":2290,"name":"Fireguard Destroyer","cnName":"火焰驱逐者","cardSet":"14","img":"fireguard-destroyer.small.png","quantity":2,"rarity":"Common","cost":4},{"dbfId":2610,"name":"Totem Golem","cnName":"图腾魔像","cardSet":"15","img":"totem-golem.small.png","quantity":2,"rarity":"Common","cost":2},{"dbfId":38263,"name":"Flamewreathed Faceless","cnName":"投火无面者","cardSet":"21","img":"flamewreathed-faceless.small.png","quantity":2,"rarity":"Common","cost":4},{"dbfId":39712,"name":"Maelstrom Portal","cnName":"大漩涡传送门","cardSet":"23","img":"maelstrom-portal.small.png","quantity":2,"rarity":"Rare","cost":2},{"dbfId":40694,"name":"Devolve","cnName":"衰变","cardSet":"25","img":"devolve.small.png","quantity":2,"rarity":"Rare","cost":2},{"dbfId":40529,"name":"Jade Claws","cnName":"青玉之爪","cardSet":"25","img":"jade-claw.small.png","quantity":2,"rarity":"Rare","cost":2},{"dbfId":40455,"name":"Jade Lightning","cnName":"青玉闪电","cardSet":"25","img":"jade-lightening.small.png","quantity":2,"rarity":"Common","cost":4},{"dbfId":47693,"name":"Genn Greymane","cnName":"吉恩·格雷迈恩","cardSet":"4","img":"genn-greymane-tab.small.png","quantity":1,"rarity":"Legendary","cost":6},{"dbfId":46996,"name":"Murkspark Eel","cnName":"阴燃电鳗","cardSet":"4","img":"muckspark-eel-tab.small.png","quantity":2,"rarity":"Rare","cost":2},{"dbfId":48527,"name":"Thunderhead","cnName":"雷云元素","cardSet":"1127","img":"thunderhead-tab.small.png","quantity":2,"rarity":"Epic","cost":4},{"dbfId":48518,"name":"Weaponized Piñata","cnName":"武装皮纳塔","cardSet":"1127","img":"weaponized-pinata-tab.small.png","quantity":1,"rarity":"Epic","cost":4},{"dbfId":54009,"name":"EVIL Totem","cnName":"怪盗图腾","cardSet":"1158","img":"evil-totem.small.png","quantity":2,"rarity":"Common","cost":2},{"dbfId":53978,"name":"Totemic Surge","cnName":"图腾潮涌","cardSet":"1158","img":"totemic-surge.small.png","quantity":2,"rarity":"Common","cost":0},{"dbfId":53990,"name":"Vessina","cnName":"维西纳","cardSet":"1158","img":"vessina.small.png","quantity":1,"rarity":"Legendary","cost":4}],"code":"AAEBAaoIBNYPzfQChvsC5qUDDdMB8hGyFPeqAvuqAqC2Aoe8AtG8Ava9ApTvAo/7AtqlA/mlAwA="}],"Priest":[{"name":"Big Priest &#x2013; slizzle466","cards":[{"dbfId":1189,"name":"Silence","cnName":"沉默","cardSet":"3","img":"silence.small.png","quantity":1,"rarity":"Common","cost":0},{"dbfId":1363,"name":"Shadow Word: Death","cnName":"暗言术：灭","cardSet":"2","img":"shadow-word-death.small.png","quantity":1,"rarity":"Basic","cost":3},{"dbfId":1367,"name":"Shadow Word: Pain","cnName":"暗言术：痛","cardSet":"2","img":"shadow-word-pain.small.png","quantity":2,"rarity":"Basic","cost":2},{"dbfId":2298,"name":"Resurrect","cnName":"复活术","cardSet":"14","img":"resurrect.small.png","quantity":2,"rarity":"Rare","cost":2},{"dbfId":38312,"name":"Y'Shaarj, Rage Unbound","cnName":"亚煞极","cardSet":"21","img":"yshaarj-rage-unbound.small.png","quantity":1,"rarity":"Legendary","cost":10},{"dbfId":39941,"name":"Barnes","cnName":"巴内斯","cardSet":"23","img":"barnes.small.png","quantity":1,"rarity":"Legendary","cost":5},{"dbfId":41169,"name":"Shadow Visions","cnName":"暗影视界","cardSet":"27","img":"shadow-visions.small.png","quantity":2,"rarity":"Epic","cost":2},{"dbfId":42597,"name":"Eternal Servitude","cnName":"永恒奴役","cardSet":"1001","img":"eternal-servitude-tab.small.png","quantity":2,"rarity":"Rare","cost":4},{"dbfId":42598,"name":"Obsidian Statue","cnName":"黑曜石雕像","cardSet":"1001","img":"obsidian-statue-tab.small.png","quantity":2,"rarity":"Epic","cost":9},{"dbfId":42804,"name":"Shadow Essence","cnName":"暗影精华","cardSet":"1001","img":"shadow-essence-tab.small.png","quantity":2,"rarity":"Rare","cost":6},{"dbfId":42818,"name":"The Lich King","cnName":"巫妖王","cardSet":"1001","img":"the-lich-king-tab.small.png","quantity":1,"rarity":"Legendary","cost":8},{"dbfId":43112,"name":"Psychic Scream","cnName":"心灵尖啸","cardSet":"1004","img":"psychic-scream-tab.small.png","quantity":2,"rarity":"Epic","cost":7},{"dbfId":46307,"name":"Lesser Diamond Spellstone","cnName":"小型法术钻石","cardSet":"1004","img":"lesser-diamon-spellstone-tab.small.png","quantity":2,"rarity":"Epic","cost":7},{"dbfId":50071,"name":"Mass Hysteria","cnName":"群体狂乱","cardSet":"1129","img":"mass-hysteria.small.png","quantity":2,"rarity":"Rare","cost":5},{"dbfId":52438,"name":"Archmage Vargoth","cnName":"大法师瓦格斯","cardSet":"1130","img":"archmage-vargoth.small.png","quantity":1,"rarity":"Legendary","cost":4},{"dbfId":52627,"name":"Catrina Muerte","cnName":"亡者卡特琳娜","cardSet":"1130","img":"catrina-muerte.small.png","quantity":1,"rarity":"Legendary","cost":8},{"dbfId":52632,"name":"Forbidden Words","cnName":"禁忌咒文","cardSet":"1130","img":"forbidden-words.small.png","quantity":2,"rarity":"Rare","cost":0},{"dbfId":53971,"name":"Holy Ripple","cnName":"神圣涟漪","cardSet":"1158","img":"holy-ripple.small.png","quantity":2,"rarity":"Rare","cost":2},{"dbfId":54431,"name":"Plague of Death","cnName":"死亡之灾祸","cardSet":"1158","img":"plague-of-death.small.png","quantity":1,"rarity":"Epic","cost":9}],"code":"AAEBAa0GCKUJ0wqoqwKFuALCzgLWmQOTmwOfqQML1wr6EdHBAuXMAubMArTOAujQAuPpApeHA5ibA9OlAwA="}]}